docketanalyzer_chat/__init__.py
docketanalyzer_chat/agent.py
docketanalyzer_chat/chat.py
docketanalyzer_chat/tool.py
docketanalyzer_chat-0.1.1.dist-info/METADATA
docketanalyzer_chat-0.1.1.dist-info/WHEEL
docketanalyzer_chat-0.1.1.dist-info/licenses/LICENSE
docketanalyzer_chat-0.1.1.dist-info/RECORD
